torpedomsg/__init__.py
torpedomsg-0.6.dist-info/DESCRIPTION.rst
torpedomsg-0.6.dist-info/METADATA
torpedomsg-0.6.dist-info/RECORD
torpedomsg-0.6.dist-info/WHEEL
torpedomsg-0.6.dist-info/metadata.json
torpedomsg-0.6.dist-info/top_level.txt
