Metadata-Version: 2.0
Name: torpedomsg
Version: 0.6
Summary: Flexible Pub-Sub on top of Tornado
Home-page: https://github.com/misuzu/torpedomsg
Author: misuzu
Author-email: UNKNOWN
License: MIT
Download-URL: https://github.com/misuzu/torpedomsg/tarball/0.6
Platform: UNKNOWN
Classifier: Development Status :: 4 - Beta
Classifier: Intended Audience :: Developers
Classifier: Natural Language :: English
Classifier: License :: OSI Approved :: MIT License
Classifier: Operating System :: OS Independent
Classifier: Programming Language :: Python
Classifier: Programming Language :: Python :: 2
Classifier: Programming Language :: Python :: 2.7
Classifier: Programming Language :: Python :: 3
Classifier: Programming Language :: Python :: 3.4
Classifier: Programming Language :: Python :: 3.5
Classifier: Topic :: Software Development :: Libraries :: Python Modules
Requires-Dist: cbor (<2)
Requires-Dist: tornado (<5)
